{
    "list":[
    {"subject":"physics",
        "subjectTopics" : [{
        "unit":"1",
        "topics":[{"name":"Fundamental & Derived Physical Quantities","id":"JieVY0q1Ypg?si=7eYmryR4WJksvNW2"},{"name":"SI units","id":"shorts/-q0oVA1X56w"},{"name":"Dimension formula trick","id":"bNaRUh8T_wQ"},
        {"name":"Principle of homogeneity","id":"kryzkVMK5k0"},{"name":"Applications of dimensional analysis","id":"4DBTfHNDMyA"},
        {"name":"Limitations of dimensional analysis","id":"U8eneC_lPkk"}]
    }]
    }
    ]
}